abbreader/__init__.py
abbreader/abbreader.py
abbreader-0.1.3.dist-info/WHEEL
abbreader-0.1.3.dist-info/METADATA
abbreader-0.1.3.dist-info/RECORD
