Metadata-Version: 2.1
Name: abbreader
Version: 0.1.3
Summary: abb reader
Author: John N
Author-email: niedrachj@gmail.com
Requires-Python: >=3.9,<4.0
Classifier: Programming Language :: Python :: 3
Classifier: Programming Language :: Python :: 3.10
Classifier: Programming Language :: Python :: 3.9
Requires-Dist: bs4 (>=0.0.1,<0.0.2)
Requires-Dist: furl (>=2.1.3,<3.0.0)
Requires-Dist: pendulum (>=2.1.2,<3.0.0)
Requires-Dist: requests (>=2.28.1,<3.0.0)
